
## 1. 람다식을 쓰고 컴파일해보자.

람다식이나 메서드 참조는 인텔리제이가 변환해줘서 많이 써왔고 어떤식으로 동작하는지 대충 알지만, 정확히 이게 어떤식으로 작동하는지 내부에서는 어떤식으로 이걸 움직이는지 몰랐다. 그래서 공부해봤다.

예전에 썻던 그 예제 그대로 써봤다.
```java
public class Main {  
    public Main() {  
    }  
    public static int add(int a, int b) {  
        return a + b;  
    }  
  
    public static void main(String[] args) {  
        BiFunction<Integer, Integer, Integer> add = Main::add;  
        System.out.println(add.apply(1, 2));  
        BiFunction<Integer, Integer, Integer> multi = (a, b) -> a * b;  
        System.out.println(multi.apply(1, 2));  
    }  
  
    public static void performOperation(int a, int b, BiFunction<Integer, Integer, Integer> operation) {  
        System.out.println(operation.apply(a, b));  
    }  
}
```
일단 `::` 이나 `->` 모두 어떤건지 보면 `BiFunction` 이것임을 알 수 있었다. 그럼 정확하게 얘는 어떤식으로 작동할까

아래는 javap를 사용하여 위의 코드를 디스어셈블한 것이다. 
```java
  public static void main(java.lang.String[]);
    Code:
       0: invokedynamic #7,  0              // InvokeDynamic #0:apply:()Ljava/util/function/BiFunction;
       5: astore_1
       6: getstatic     #11                 // Field java/lang/System.out:Ljava/io/PrintStream;
       9: aload_1
      10: iconst_1
      11: invokestatic  #17                 // Method java/lang/Integer.valueOf:(I)Ljava/lang/Integer;
		...
```
`0: invokedynamic`에 주목하자. 이 바이트코드가 람다식에 해당하는 바이트코드이다.  `invokedynamic` 명령어는 런타임에 메서드 핸들을 동적으로 바인딩한다. 람다식은 이 명령어를 통해 `java.lang.invoke.LambdaMetafactory`에서 생성된 **메서드 핸들**로 연결된다.


---
## 2. 람다식과 익명클래스의 차이

흔히 강의를 듣거나 하다보면 익명클래스 = 람다식이라고 생각하라는 말을 많이 들어왔다. 쓰임새도 비슷하고 하니 그동안 그렇게 생각했다. 그런데 이번에 공부하면서 둘은 꽤 많이 다름을 알게 되었다.

```java
// 익명 클래스 
Function<Integer, Integer> squareWithAnonymousClass = new Function<>() {   
	@Override     
	public Integer apply(Integer x) {
         return x * x;
	    }
    };
```

익명 클래스를 쓰면 클래스 파일이 하나 생긴다. ClassName$1.class 이런식으로. 그런데 둘이 같은거면 람다식을 쓸 때도 클래스가 생겨야 하지 않을까? 그런데 안생긴다. 둘의 차이점에 대한 표가 아래에 있다.
### 1) **람다식과 익명 클래스의 차이**

|**특징**|**익명 클래스**|**람다식**|
|---|---|---|
|**구현 방식**|컴파일 시 별도의 `.class` 파일(익명 클래스)이 생성됨|`invokedynamic` 명령어를 사용해 런타임에 메서드 핸들로 생성|
|**메모리 사용**|별도의 클래스 로딩과 인스턴스 생성 비용이 발생|메서드 핸들로 처리되므로 메모리 사용량이 적음|
|**동작 방식**|익명 클래스의 객체를 생성해 실행|`LambdaMetafactory`가 최적화된 바이트코드를 생성|
|**사용 용도**|인터페이스 구현뿐 아니라 상속을 통해 다양한 기능 가능|함수형 인터페이스와 함께 사용하여 함수형 프로그래밍에 적합|
|**`this` 키워드**|익명 클래스 내부에서 익명 클래스 인스턴스를 참조|람다식 내부에서 외부의 `this`를 참조|

### 2) **람다식이 익명 클래스와 다른 이유**

1. **`invokedynamic` 기반**
    - 람다식은 익명 클래스처럼 추가적인 `.class` 파일을 생성하지 않는다.
    - JVM의 `invokedynamic` 명령어와 `LambdaMetafactory`를 통해 런타임에 동적으로 메서드 핸들을 생성한다.

2. **클래스 상속과 차이점**
    - 익명 클래스는 **상속**을 통해 부모 클래스나 인터페이스를 구현하는 데 사용된다.
    - 람다식은 **함수형 인터페이스(단일 추상 메서드 인터페이스)**만을 대상으로 동작합니다.

3. **`this` 키워드 동작**
    - 익명 클래스 내부의 `this`는 익명 클래스 자체를 가리킨다.
    - 람다식 내부의 `this`는 람다식을 포함하는 **외부 클래스**를 가리킨다.

### 3) **정리**

람다식이 익명 클래스의 단순한 요약이라고 말하는 것은 **람다식의 본질을 축소하는 표현**이다.

- 익명 클래스는 **객체 지향적인 클래스 인스턴스 생성** 방식이고,
- 람다식은 **함수형 프로그래밍**을 Java에 구현하기 위한 새로운 동작 방식입니다.

람다식은 **동작의 표현을 간소화**하면서도 성능 최적화와 유연성을 제공하기 위해 만들어졌으며, 익명 클래스를 대체하기보다는 **함수형 인터페이스를 활용하기 위한 새로운 도구**로 설계되었다.

---

## 3. invokedynamic

`invokedynamic`에 대해 더 깊이 이해하려면, 이 명령어가 **왜 필요한지**, **어떻게 동작하는지**, 그리고 **Java에서 어떤 문제를 해결하려고 도입되었는지**를 알아야 합니다. 아래에서 구체적으로 알아보자.

---
### **1. `invokedynamic`의 도입 배경**

`invokedynamic`은 **Java 7**에 도입된 바이트코드 명령어로, 동적 언어의 메서드 호출을 지원하기 위해 만들어졌다.

#### 1) **전통적인 Java 메서드 호출의 한계**

Java는 정적 타입 언어이기 때문에 메서드 호출 방식이 **컴파일 시점**에 고정된다. 예를 들어:
- `invokevirtual`: 객체의 인스턴스 메서드를 호출.
- `invokestatic`: 클래스의 정적 메서드를 호출.
- `invokeinterface`: 인터페이스의 메서드를 호출.

#### 2) **동적 언어와의 차이점**

Python, Ruby, Groovy 같은 동적 언어는 **런타임에 메서드를 찾고 실행**한다. 이를 Java의 정적 호출 방식으로 흉내내기 위해서는 추가적인 코드를 작성하거나 성능 문제가 발생할 수 있었다.

### **2. `invokedynamic`의 역할**

`invokedynamic`은 메서드 호출 방식을 컴파일 시점에 고정하지 않고, **런타임에 메서드를 동적으로 연결**할 수 있게 해준다.

#### **이점**

1. 동적 메서드 호출이 가능 (Python, Groovy 같은 동적 언어와의 호환성).
2. 람다식 같은 동작 중심의 표현을 효율적으로 처리.
3. JVM이 런타임에 최적화된 메서드 핸들을 생성하여 성능을 향상.

---

### **3. `invokedynamic`의 작동 원리**

`invokedynamic` 명령어는 다음 3단계를 거쳐 메서드를 호출한다.

#### **1단계: 부트스트랩 메서드 (Bootstrap Method)**

`invokedynamic`은 **부트스트랩 메서드(Bootstrap Method)**를 호출하여 동적 메서드 핸들을 생성한다.

- 부트스트랩 메서드는 어떤 메서드 핸들을 생성할지 결정하는 초기화 역할을 한다.
- 부트스트랩 메서드의 구현체는 **`java.lang.invoke.LambdaMetafactory`** 같은 클래스에 존재한다.

#### **2단계: 런타임에 메서드 핸들 생성**

- 부트스트랩 메서드는 런타임에 필요한 메서드 핸들을 생성하고 이를 반환한다.
- 메서드 핸들은 이후 동일한 호출에 대해 캐싱되어 재사용된다.

#### **3단계: 메서드 호출**

- 생성된 메서드 핸들을 통해 실제 메서드 호출이 이루어진다.

---

### **4. 예제: 람다식과 `invokedynamic`의 관계**

다음은 람다식을 사용한 Java 코드를 바이트코드로 분석한 예이다.

#### **Java 코드**

```java
import java.util.function.Function;

public class Main {
    public static void main(String[] args) {
        Function<Integer, Integer> square = x -> x * x;
        System.out.println(square.apply(5));
    }
}
```

#### **바이트코드 (`javap -c Main`)**

```plaintext
  0: invokedynamic #2,  0 // InvokeDynamic #0:apply:()Ljava/util/function/Function;
  5: astore_1
  6: getstatic     #3    // Field java/lang/System.out:Ljava/io/PrintStream;
  9: aload_1
 10: iconst_5
 11: invokestatic  #4    // Method java/lang/Integer.valueOf:(I)Ljava/lang/Integer;
 14: invokeinterface #5,  2 // InterfaceMethod java/util/function/Function.apply:(Ljava/lang/Object;)Ljava/lang/Object;
```

#### **분석**

1. **`invokedynamic` 명령어 (라인 0):**
    
    - `LambdaMetafactory`에서 `Function.apply` 구현체를 생성.
    - 런타임에 `x -> x * x` 람다식을 처리하기 위한 메서드 핸들을 생성.
2. **`LambdaMetafactory` 역할:**
    
    - 부트스트랩 메서드 역할을 하며, `apply` 메서드 핸들을 생성.
    - 생성된 메서드 핸들은 `Function<Integer, Integer>` 타입으로 반환.
3. **람다식 실행 (라인 14):**
    
    - `Function.apply`를 호출하여 람다식을 실행.

---

### **5. 부트스트랩 메서드의 동작**

부트스트랩 메서드는 런타임에 `invokedynamic` 명령어가 호출될 때 실행되며, 호출 대상 메서드를 동적으로 연결한다.

#### **부트스트랩 메서드 정의**

`java.lang.invoke.LambdaMetafactory.metafactory`가 부트스트랩 메서드로 작동한다.

```java
public static CallSite metafactory(MethodHandles.Lookup caller,
                                   String invokedName,
                                   MethodType invokedType,
                                   MethodType samMethodType,
                                   MethodHandle implMethod,
                                   MethodType instantiatedMethodType);
```

- **`caller`**: 호출하는 클래스의 정보를 나타냄.
- **`invokedName`**: 호출하려는 메서드의 이름.
- **`invokedType`**: 호출하려는 메서드의 타입.
- **`implMethod`**: 실제 구현 메서드의 핸들(MethodHandle).
- **`samMethodType`**: 함수형 인터페이스의 추상 메서드 타입.

---

### **6. 주요 용도**

1. **람다식 처리**
    - `invokedynamic`은 `LambdaMetafactory`를 통해 람다식 구현체를 동적으로 생성.
    - 이는 별도의 클래스를 생성하지 않으므로 메모리 효율적.
    
2. **동적 언어 지원**
    - `invokedynamic`은 Python, Groovy, JRuby 같은 동적 언어에서 메서드 호출을 처리하는 기반으로 사용.

3. **메서드 핸들 활용**
    
    - 런타임에 최적화된 메서드 핸들을 생성하고 재사용하여 성능 향상.

이제 `invokedynamic`은 단순히 메서드 핸들을 동적으로 생성하고 호출하는 것이 아니라, **Java가 정적 언어에서 동적 언어의 특징을 수용하는 기반 기술**임을 알 수 있다.

---
---

![[Pasted image 20241211174330.png]]

위 다이어그램은 **`invokedynamic`과 람다식의 실행 과정**을 순서도로 나타낸 것이다. 각 단계는 아래와 같다:

---

### **1. Java Source Code**
- Java 코드에서 람다식을 작성한다.
- 예: `Function<Integer, Integer> square = x -> x * x;`

### **2. Compilation (`javac`)**
- 컴파일러가 람다식을 포함한 Java 코드를 **바이트코드**로 변환한다.

### **3. Bytecode (`invokedynamic`)**
- 변환된 바이트코드에는 람다식을 처리하기 위해 `invokedynamic` 명령어가 포함된다.

### **4. Bootstrap Method**
- `invokedynamic` 명령어가 실행될 때 **Bootstrap Method**를 호출하여 동적 메서드 핸들을 생성한다.
- 기본적으로 `LambdaMetafactory.metafactory`가 부트스트랩 메서드로 사용된다.

### **5. Method Handles**
- 부트스트랩 메서드는 **메서드 핸들(Method Handle)**을 생성하여, 실제 람다식 구현체를 동적으로 연결한다.

### **6. Generated Lambda Implementation Class**
- 런타임에 람다식을 위한 익명 클래스(또는 인스턴스)가 동적으로 생성된다.
- 예: `Lambda$1` 같은 이름의 클래스가 생성될 수 있다.

### **7. Lambda Execution**
- 생성된 람다 구현체가 실행되며, 작성된 람다식의 로직이 수행된다.
---

### **컴파일과 실행의 관계**

1. **컴파일 단계 (2번)**:
    - **컴파일러(`javac`)** 는 Java 소스 코드를 읽고, 이를 **바이트코드**로 변환한다.
    - 컴파일된 바이트코드 안에는 **`invokedynamic` 명령어**가 포함된다.
    - 이 단계에서는 단순히 바이트코드 생성이 이루어질 뿐, 람다식의 실제 동작은 결정되지 않는다.
      
2. **실행 단계 (3번 이후)**:
    - 프로그램을 실행하면 JVM이 바이트코드를 해석하면서 **`invokedynamic` 명령어**를 만나게 된다.
    - **`invokedynamic` 명령어**가 실행되면서:
        - 부트스트랩 메서드가 호출된다.
        - 메서드 핸들이 생성되고, 동적으로 람다식 구현체가 만들어진다.
    - 이후, 생성된 람다 구현체가 호출되고, 람다식의 실제 로직이 수행된다.

---

### **단계 구분**

|단계|작업 내용|실행 시점|
|---|---|---|
|**2. Compilation (javac)**|Java 소스 코드를 바이트코드로 변환.|컴파일 시점|
|**3. Bytecode (invokedynamic)**|바이트코드를 해석하고, 동적 메서드 호출 준비.|실행 시점|
|**4~6. 동적 생성 과정**|부트스트랩 메서드 호출 → 메서드 핸들 생성 → 람다 구현체 생성.|실행 시점|
|**7. Lambda Execution**|생성된 람다 구현체를 실행.|실행 시점|

---

### **예를 들어 보자**

#### **Java 코드 (컴파일 단계)**

```java
Function<Integer, Integer> square = x -> x * x;
```

- **컴파일러가 변환한 바이트코드**:
    
    ```plaintext
    invokedynamic #2, 0 // InvokeDynamic #0:apply:()Ljava/util/function/Function;
    ```
    

#### **프로그램 실행 시 (3번 이후)**

- JVM이 `invokedynamic` 명령어를 실행:
    - **부트스트랩 메서드**: `LambdaMetafactory.metafactory` 호출.
    - **메서드 핸들 생성**: 람다식의 실제 구현체 생성.
    - 람다 구현체 실행: `square.apply(5)` 호출 → 결과 `25`.

---

### **결론**

- **컴파일 단계**는 **2번(Compilation)** 에 해당하며, 바이트코드 안에 `invokedynamic` 명령어를 포함한다.
- **실행 단계**는 **3번 이후**로, 실제로 JVM이 `invokedynamic` 명령어를 처리하고, 람다식 동작을 실행한다.

이 구조는 JVM의 유연성을 제공하면서도, **런타임에서 최적화된 람다 구현체를 동적으로 생성**할 수 있게 한다.
