람다식이나 메서드 참조는 인텔리제이가 변환해줘서 많이 써왔고 어떤식으로 동작하는지 대충 알지만, 정확히 이게 어떤식으로 작동하는지 내부에서는 어떤식으로 이걸 움직이는지 몰랐다. 그래서 공부해봤다.

예전에 썻던 그 예제 그대로 써봤다.
```java
public class Main {  
    public Main() {  
    }  
    public static int add(int a, int b) {  
        return a + b;  
    }  
  
    public static void main(String[] args) {  
        BiFunction<Integer, Integer, Integer> add = Main::add;  
        System.out.println(add.apply(1, 2));  
        BiFunction<Integer, Integer, Integer> multi = (a, b) -> a * b;  
        System.out.println(multi.apply(1, 2));  
    }  
  
    public static void performOperation(int a, int b, BiFunction<Integer, Integer, Integer> operation) {  
        System.out.println(operation.apply(a, b));  
    }  
}
```
일단 `::` 이나 `->` 모두 어떤건지 보면 `BiFunction` 이것임을 알 수 있었다. 그럼 정확하게 얘는 어떤식으로 작동할까

javap를 사용하여 컴파일해봤다.
```java
public class Main {
  public Main();
    Code:
       0: aload_0
       1: invokespecial #1                  // Method java/lang/Object."<init>":()V
       4: return

  public static int add(int, int);
    Code:
       0: iload_0
       1: iload_1
       2: iadd
       3: ireturn

  public static void main(java.lang.String[]);
    Code:
       0: invokedynamic #7,  0              // InvokeDynamic #0:apply:()Ljava/util/function/BiFunction;
       5: astore_1
       6: getstatic     #11                 // Field java/lang/System.out:Ljava/io/PrintStream;
       9: aload_1
      10: iconst_1
      11: invokestatic  #17                 // Method java/lang/Integer.valueOf:(I)Ljava/lang/Integer;
      14: iconst_2
      15: invokestatic  #17                 // Method java/lang/Integer.valueOf:(I)Ljava/lang/Integer;
      18: invokeinterface #23,  3           // InterfaceMethod java/util/function/BiFunction.apply:(Ljava/lang/Object;Ljava/lang/Object;)Ljava/lang/Object;
      23: invokevirtual #28                 // Method java/io/PrintStream.println:(Ljava/lang/Object;)V
      26: invokedynamic #34,  0             // InvokeDynamic #1:apply:()Ljava/util/function/BiFunction;
      31: astore_2
      32: getstatic     #11                 // Field java/lang/System.out:Ljava/io/PrintStream;
      35: aload_2
      36: iconst_1
      37: invokestatic  #17                 // Method java/lang/Integer.valueOf:(I)Ljava/lang/Integer;
      40: iconst_2
      41: invokestatic  #17                 // Method java/lang/Integer.valueOf:(I)Ljava/lang/Integer;
      44: invokeinterface #23,  3           // InterfaceMethod java/util/function/BiFunction.apply:(Ljava/lang/Object;Ljava/lang/Object;)Ljava/lang/Object;
      49: invokevirtual #28                 // Method java/io/PrintStream.println:(Ljava/lang/Object;)V
      52: return

  public static void performOperation(int, int, java.util.function.BiFunction<java.lang.Integer, java.lang.Integer, java.lang.Integer>);
    Code:
       0: getstatic     #11                 // Field java/lang/System.out:Ljava/io/PrintStream;
       3: aload_2
       4: iload_0
       5: invokestatic  #17                 // Method java/lang/Integer.valueOf:(I)Ljava/lang/Integer;
       8: iload_1
       9: invokestatic  #17                 // Method java/lang/Integer.valueOf:(I)Ljava/lang/Integer;
      12: invokeinterface #23,  3           // InterfaceMethod java/util/function/BiFunction.apply:(Ljava/lang/Object;Ljava/lang/Object;)Ljava/lang/Object;
      17: invokevirtual #28                 // Method java/io/PrintStream.println:(Ljava/lang/Object;)V
      20: return
}

```